micro_graph/__init__.py
micro_graph/micro_graph.py
micro_graph/output_writer.py
micro_graph/ai/__init__.py
micro_graph/ai/automatic_refinement_feedback_loop.py
micro_graph/ai/llm.py
micro_graph/ai/llm_generation.py
micro_graph/ai/mcp.py
micro_graph/ai/openai_server.py
micro_graph/ai/types.py
micro_graph/io/__init__.py
micro_graph/io/cli_input.py
micro_graph-0.3.1.dist-info/METADATA
micro_graph-0.3.1.dist-info/WHEEL
micro_graph-0.3.1.dist-info/licenses/LICENSE
micro_graph-0.3.1.dist-info/RECORD
