Metadata-Version: 2.4
Name: micro-graph
Version: 0.3.1
Summary: A simple library to build compute graphs for logical flows like agents.
Author: Michael Fuerst
Maintainer: Michael Fuerst
License-Expression: MIT
License-File: LICENSE
Keywords: ai,graph,low-code
Requires-Python: >=3.10
Provides-Extra: ai
Requires-Dist: dotenv>=0.9.9; extra == 'ai'
Requires-Dist: fastapi>=0.116.1; extra == 'ai'
Requires-Dist: fastmcp>=2.10.6; extra == 'ai'
Requires-Dist: openai>=1.98.0; extra == 'ai'
Requires-Dist: requests>=2.32.4; extra == 'ai'
Requires-Dist: uvicorn>=0.34.0; extra == 'ai'
Provides-Extra: dev
Requires-Dist: pre-commit>=4.2.0; extra == 'dev'
Requires-Dist: pytest-asyncio>=1.1.0; extra == 'dev'
Requires-Dist: pytest>=8.4.1; extra == 'dev'
Requires-Dist: ruff>=0.12.7; extra == 'dev'
